Metadata-Version: 2.2
Name: sqlite-utils-tui
Version: 0.1
Summary: Terminal UI for sqlite-utils
Author: Simon Willison
License: Apache-2.0
Project-URL: Homepage, https://github.com/simonw/sqlite-utils-tui
Project-URL: Changelog, https://github.com/simonw/sqlite-utils-tui/releases
Project-URL: Issues, https://github.com/simonw/sqlite-utils-tui/issues
Project-URL: CI, https://github.com/simonw/sqlite-utils-tui/actions
Classifier: License :: OSI Approved :: Apache Software License
License-File: LICENSE
Requires-Dist: sqlite-utils
Requires-Dist: trogon>=0.6.0
Provides-Extra: test
Requires-Dist: pytest; extra == "test"
